AUTHORS.md
CONTRIBUTING.md
HISTORY.md
LICENSE
MANIFEST.in
README.md
setup.py
disposable_email_checker/__init__.py
disposable_email_checker/emails.py
disposable_email_checker/fields.py
disposable_email_checker/forms.py
disposable_email_checker/models.py
disposable_email_checker/validators.py
django_email_disposable_checker.egg-info/PKG-INFO
django_email_disposable_checker.egg-info/SOURCES.txt
django_email_disposable_checker.egg-info/dependency_links.txt
django_email_disposable_checker.egg-info/not-zip-safe
django_email_disposable_checker.egg-info/requires.txt
django_email_disposable_checker.egg-info/top_level.txt
tests/test_validators.py