Metadata-Version: 2.1
Name: django-email-disposable-checker
Version: 0.0.1
Summary: Django package to detect ~890 domains used by disposable email services
Home-page: https://github.com/jheld/DisposableEmailChecker
Author: Jason Held
Author-email: jasonsheld@gmail.com
License: BSD
Keywords: DisposableEmailChecker
Classifier: Development Status :: 5 - Production/Stable
Classifier: Framework :: Django
Classifier: Intended Audience :: Developers
Classifier: License :: OSI Approved :: BSD License
Classifier: Natural Language :: English
Classifier: Programming Language :: Python :: 3.7
Classifier: Programming Language :: Python :: 3.8
License-File: LICENSE
License-File: AUTHORS.md
